{
  "version": "6",
  "dialect": "sqlite",
  "id": "61a49754-3fad-40d4-95ac-ae22a3feaef2",
  "prevId": "78f29f6f-e5d4-4048-a9c8-38b3a1228b9b",
  "tables": {
    "ai_plan_drafts": {
      "name": "ai_plan_drafts",
      "columns": {
        "id": {
          "name": "id",
          "type": "integer",
          "primaryKey": true,
          "notNull": true,
          "autoincrement": true
        },
        "session_id": {
          "name": "session_id",
          "type": "text",
          "primaryKey": false,
          "notNull": true,
          "autoincrement": false
        },
        "user_id": {
          "name": "user_id",
          "type": "integer",
          "primaryKey": false,
          "notNull": true,
          "autoincrement": false
        },
        "draft": {
          "name": "draft",
          "type": "text",
          "primaryKey": false,
          "notNull": true,
          "autoincrement": false
        },
        "created_at": {
          "name": "created_at",
          "type": "integer",
          "primaryKey": false,
          "notNull": true,
          "autoincrement": false,
          "default": "(unixepoch())"
        },
        "updated_at": {
          "name": "updated_at",
          "type": "integer",
          "primaryKey": false,
          "notNull": true,
          "autoincrement": false,
          "default": "(unixepoch())"
        }
      },
      "indexes": {
        "ai_plan_drafts_session_user_uniq": {
          "name": "ai_plan_drafts_session_user_uniq",
          "columns": [
            "session_id",
            "user_id"
          ],
          "isUnique": true
        },
        "ai_plan_drafts_user_idx": {
          "name": "ai_plan_drafts_user_idx",
          "columns": [
            "user_id"
          ],
          "isUnique": false
        }
      },
      "foreignKeys": {},
      "compositePrimaryKeys": {},
      "uniqueConstraints": {},
      "checkConstraints": {}
    },
    "auth_accounts": {
      "name": "auth_accounts",
      "columns": {
        "id": {
          "name": "id",
          "type": "integer",
          "primaryKey": true,
          "notNull": true,
          "autoincrement": true
        },
        "user_id": {
          "name": "user_id",
          "type": "integer",
          "primaryKey": false,
          "notNull": true,
          "autoincrement": false
        },
        "provider": {
          "name": "provider",
          "type": "text",
          "primaryKey": false,
          "notNull": true,
          "autoincrement": false
        },
        "provider_account_id": {
          "name": "provider_account_id",
          "type": "text",
          "primaryKey": false,
          "notNull": true,
          "autoincrement": false
        },
        "secret": {
          "name": "secret",
          "type": "text",
          "primaryKey": false,
          "notNull": false,
          "autoincrement": false
        },
        "email_verified": {
          "name": "email_verified",
          "type": "text",
          "primaryKey": false,
          "notNull": false,
          "autoincrement": false
        },
        "phone_verified": {
          "name": "phone_verified",
          "type": "text",
          "primaryKey": false,
          "notNull": false,
          "autoincrement": false
        },
        "created_at": {
          "name": "created_at",
          "type": "integer",
          "primaryKey": false,
          "notNull": true,
          "autoincrement": false,
          "default": "(unixepoch())"
        }
      },
      "indexes": {
        "auth_accounts_user_idx": {
          "name": "auth_accounts_user_idx",
          "columns": [
            "user_id"
          ],
          "isUnique": false
        },
        "auth_accounts_provider_idx": {
          "name": "auth_accounts_provider_idx",
          "columns": [
            "provider",
            "provider_account_id"
          ],
          "isUnique": false
        }
      },
      "foreignKeys": {},
      "compositePrimaryKeys": {},
      "uniqueConstraints": {},
      "checkConstraints": {}
    },
    "auth_sessions": {
      "name": "auth_sessions",
      "columns": {
        "id": {
          "name": "id",
          "type": "integer",
          "primaryKey": true,
          "notNull": true,
          "autoincrement": true
        },
        "user_id": {
          "name": "user_id",
          "type": "integer",
          "primaryKey": false,
          "notNull": true,
          "autoincrement": false
        },
        "expiration_time": {
          "name": "expiration_time",
          "type": "integer",
          "primaryKey": false,
          "notNull": true,
          "autoincrement": false
        },
        "created_at": {
          "name": "created_at",
          "type": "integer",
          "primaryKey": false,
          "notNull": true,
          "autoincrement": false,
          "default": "(unixepoch())"
        }
      },
      "indexes": {
        "auth_sessions_user_idx": {
          "name": "auth_sessions_user_idx",
          "columns": [
            "user_id"
          ],
          "isUnique": false
        }
      },
      "foreignKeys": {},
      "compositePrimaryKeys": {},
      "uniqueConstraints": {},
      "checkConstraints": {}
    },
    "rate_limits": {
      "name": "rate_limits",
      "columns": {
        "id": {
          "name": "id",
          "type": "integer",
          "primaryKey": true,
          "notNull": true,
          "autoincrement": true
        },
        "key": {
          "name": "key",
          "type": "text",
          "primaryKey": false,
          "notNull": true,
          "autoincrement": false
        },
        "count": {
          "name": "count",
          "type": "integer",
          "primaryKey": false,
          "notNull": true,
          "autoincrement": false,
          "default": 0
        },
        "expires_at": {
          "name": "expires_at",
          "type": "integer",
          "primaryKey": false,
          "notNull": true,
          "autoincrement": false
        },
        "created_at": {
          "name": "created_at",
          "type": "integer",
          "primaryKey": false,
          "notNull": true,
          "autoincrement": false,
          "default": "(unixepoch())"
        }
      },
      "indexes": {
        "rate_limits_key_idx": {
          "name": "rate_limits_key_idx",
          "columns": [
            "key"
          ],
          "isUnique": false
        }
      },
      "foreignKeys": {},
      "compositePrimaryKeys": {},
      "uniqueConstraints": {},
      "checkConstraints": {}
    },
    "users": {
      "name": "users",
      "columns": {
        "id": {
          "name": "id",
          "type": "integer",
          "primaryKey": true,
          "notNull": true,
          "autoincrement": true
        },
        "name": {
          "name": "name",
          "type": "text",
          "primaryKey": false,
          "notNull": false,
          "autoincrement": false
        },
        "email": {
          "name": "email",
          "type": "text",
          "primaryKey": false,
          "notNull": false,
          "autoincrement": false
        },
        "email_verification_time": {
          "name": "email_verification_time",
          "type": "integer",
          "primaryKey": false,
          "notNull": false,
          "autoincrement": false
        },
        "phone": {
          "name": "phone",
          "type": "text",
          "primaryKey": false,
          "notNull": false,
          "autoincrement": false
        },
        "phone_verification_time": {
          "name": "phone_verification_time",
          "type": "integer",
          "primaryKey": false,
          "notNull": false,
          "autoincrement": false
        },
        "image": {
          "name": "image",
          "type": "text",
          "primaryKey": false,
          "notNull": false,
          "autoincrement": false
        },
        "is_anonymous": {
          "name": "is_anonymous",
          "type": "integer",
          "primaryKey": false,
          "notNull": false,
          "autoincrement": false
        },
        "created_at": {
          "name": "created_at",
          "type": "integer",
          "primaryKey": false,
          "notNull": true,
          "autoincrement": false,
          "default": "(unixepoch())"
        },
        "updated_at": {
          "name": "updated_at",
          "type": "integer",
          "primaryKey": false,
          "notNull": true,
          "autoincrement": false,
          "default": "(unixepoch())"
        }
      },
      "indexes": {
        "users_email_uniq": {
          "name": "users_email_uniq",
          "columns": [
            "email"
          ],
          "isUnique": true
        },
        "users_phone_idx": {
          "name": "users_phone_idx",
          "columns": [
            "phone"
          ],
          "isUnique": false
        }
      },
      "foreignKeys": {},
      "compositePrimaryKeys": {},
      "uniqueConstraints": {},
      "checkConstraints": {}
    },
    "chat_messages": {
      "name": "chat_messages",
      "columns": {
        "id": {
          "name": "id",
          "type": "integer",
          "primaryKey": true,
          "notNull": true,
          "autoincrement": true
        },
        "session_id": {
          "name": "session_id",
          "type": "integer",
          "primaryKey": false,
          "notNull": true,
          "autoincrement": false
        },
        "role": {
          "name": "role",
          "type": "text",
          "primaryKey": false,
          "notNull": true,
          "autoincrement": false
        },
        "content": {
          "name": "content",
          "type": "text",
          "primaryKey": false,
          "notNull": true,
          "autoincrement": false
        },
        "metadata": {
          "name": "metadata",
          "type": "text",
          "primaryKey": false,
          "notNull": false,
          "autoincrement": false
        },
        "created_at": {
          "name": "created_at",
          "type": "integer",
          "primaryKey": false,
          "notNull": true,
          "autoincrement": false,
          "default": "(unixepoch())"
        }
      },
      "indexes": {
        "chat_messages_session_idx": {
          "name": "chat_messages_session_idx",
          "columns": [
            "session_id"
          ],
          "isUnique": false
        },
        "chat_messages_session_created_idx": {
          "name": "chat_messages_session_created_idx",
          "columns": [
            "session_id",
            "created_at"
          ],
          "isUnique": false
        }
      },
      "foreignKeys": {},
      "compositePrimaryKeys": {},
      "uniqueConstraints": {},
      "checkConstraints": {}
    },
    "chat_sessions": {
      "name": "chat_sessions",
      "columns": {
        "id": {
          "name": "id",
          "type": "integer",
          "primaryKey": true,
          "notNull": true,
          "autoincrement": true
        },
        "user_id": {
          "name": "user_id",
          "type": "integer",
          "primaryKey": false,
          "notNull": true,
          "autoincrement": false
        },
        "title": {
          "name": "title",
          "type": "text",
          "primaryKey": false,
          "notNull": false,
          "autoincrement": false
        },
        "is_archived": {
          "name": "is_archived",
          "type": "integer",
          "primaryKey": false,
          "notNull": true,
          "autoincrement": false,
          "default": false
        },
        "last_message_at": {
          "name": "last_message_at",
          "type": "integer",
          "primaryKey": false,
          "notNull": false,
          "autoincrement": false
        },
        "itinerary_id": {
          "name": "itinerary_id",
          "type": "integer",
          "primaryKey": false,
          "notNull": false,
          "autoincrement": false
        },
        "metadata": {
          "name": "metadata",
          "type": "text",
          "primaryKey": false,
          "notNull": false,
          "autoincrement": false
        },
        "created_at": {
          "name": "created_at",
          "type": "integer",
          "primaryKey": false,
          "notNull": true,
          "autoincrement": false,
          "default": "(unixepoch())"
        },
        "updated_at": {
          "name": "updated_at",
          "type": "integer",
          "primaryKey": false,
          "notNull": true,
          "autoincrement": false,
          "default": "(unixepoch())"
        }
      },
      "indexes": {
        "chat_sessions_user_idx": {
          "name": "chat_sessions_user_idx",
          "columns": [
            "user_id"
          ],
          "isUnique": false
        },
        "chat_sessions_user_archived_idx": {
          "name": "chat_sessions_user_archived_idx",
          "columns": [
            "user_id",
            "is_archived"
          ],
          "isUnique": false
        },
        "chat_sessions_user_last_msg_idx": {
          "name": "chat_sessions_user_last_msg_idx",
          "columns": [
            "user_id",
            "last_message_at"
          ],
          "isUnique": false
        },
        "chat_sessions_itinerary_idx": {
          "name": "chat_sessions_itinerary_idx",
          "columns": [
            "itinerary_id"
          ],
          "isUnique": false
        }
      },
      "foreignKeys": {},
      "compositePrimaryKeys": {},
      "uniqueConstraints": {},
      "checkConstraints": {}
    },
    "cities": {
      "name": "cities",
      "columns": {
        "id": {
          "name": "id",
          "type": "integer",
          "primaryKey": true,
          "notNull": true,
          "autoincrement": true
        },
        "name": {
          "name": "name",
          "type": "text",
          "primaryKey": false,
          "notNull": true,
          "autoincrement": false
        },
        "name_en": {
          "name": "name_en",
          "type": "text",
          "primaryKey": false,
          "notNull": false,
          "autoincrement": false
        },
        "timezone": {
          "name": "timezone",
          "type": "text",
          "primaryKey": false,
          "notNull": false,
          "autoincrement": false
        },
        "country_code": {
          "name": "country_code",
          "type": "text",
          "primaryKey": false,
          "notNull": false,
          "autoincrement": false
        },
        "latitude": {
          "name": "latitude",
          "type": "real",
          "primaryKey": false,
          "notNull": true,
          "autoincrement": false
        },
        "longitude": {
          "name": "longitude",
          "type": "real",
          "primaryKey": false,
          "notNull": true,
          "autoincrement": false
        },
        "utc_offset": {
          "name": "utc_offset",
          "type": "real",
          "primaryKey": false,
          "notNull": false,
          "autoincrement": false
        },
        "utc_offset_dst": {
          "name": "utc_offset_dst",
          "type": "real",
          "primaryKey": false,
          "notNull": false,
          "autoincrement": false
        },
        "has_dst": {
          "name": "has_dst",
          "type": "integer",
          "primaryKey": false,
          "notNull": false,
          "autoincrement": false,
          "default": false
        },
        "created_at": {
          "name": "created_at",
          "type": "integer",
          "primaryKey": false,
          "notNull": true,
          "autoincrement": false,
          "default": "(unixepoch())"
        },
        "updated_at": {
          "name": "updated_at",
          "type": "integer",
          "primaryKey": false,
          "notNull": true,
          "autoincrement": false,
          "default": "(unixepoch())"
        }
      },
      "indexes": {
        "cities_name_idx": {
          "name": "cities_name_idx",
          "columns": [
            "name"
          ],
          "isUnique": false
        },
        "cities_country_idx": {
          "name": "cities_country_idx",
          "columns": [
            "country_code"
          ],
          "isUnique": false
        },
        "cities_timezone_idx": {
          "name": "cities_timezone_idx",
          "columns": [
            "timezone"
          ],
          "isUnique": false
        }
      },
      "foreignKeys": {},
      "compositePrimaryKeys": {},
      "uniqueConstraints": {},
      "checkConstraints": {}
    },
    "currency_history": {
      "name": "currency_history",
      "columns": {
        "id": {
          "name": "id",
          "type": "integer",
          "primaryKey": true,
          "notNull": true,
          "autoincrement": true
        },
        "base_currency": {
          "name": "base_currency",
          "type": "text",
          "primaryKey": false,
          "notNull": true,
          "autoincrement": false
        },
        "target_currency": {
          "name": "target_currency",
          "type": "text",
          "primaryKey": false,
          "notNull": true,
          "autoincrement": false
        },
        "rate": {
          "name": "rate",
          "type": "real",
          "primaryKey": false,
          "notNull": true,
          "autoincrement": false
        },
        "days": {
          "name": "days",
          "type": "integer",
          "primaryKey": false,
          "notNull": true,
          "autoincrement": false,
          "default": 1
        },
        "fetched_at": {
          "name": "fetched_at",
          "type": "integer",
          "primaryKey": false,
          "notNull": true,
          "autoincrement": false
        },
        "created_at": {
          "name": "created_at",
          "type": "integer",
          "primaryKey": false,
          "notNull": true,
          "autoincrement": false,
          "default": "(unixepoch())"
        }
      },
      "indexes": {
        "currency_hist_pair_idx": {
          "name": "currency_hist_pair_idx",
          "columns": [
            "base_currency",
            "target_currency"
          ],
          "isUnique": false
        },
        "currency_hist_pair_days_idx": {
          "name": "currency_hist_pair_days_idx",
          "columns": [
            "base_currency",
            "target_currency",
            "days"
          ],
          "isUnique": false
        },
        "currency_hist_fetched_idx": {
          "name": "currency_hist_fetched_idx",
          "columns": [
            "fetched_at"
          ],
          "isUnique": false
        }
      },
      "foreignKeys": {},
      "compositePrimaryKeys": {},
      "uniqueConstraints": {},
      "checkConstraints": {}
    },
    "currency_rates": {
      "name": "currency_rates",
      "columns": {
        "id": {
          "name": "id",
          "type": "integer",
          "primaryKey": true,
          "notNull": true,
          "autoincrement": true
        },
        "base_currency": {
          "name": "base_currency",
          "type": "text",
          "primaryKey": false,
          "notNull": true,
          "autoincrement": false
        },
        "rates": {
          "name": "rates",
          "type": "text",
          "primaryKey": false,
          "notNull": true,
          "autoincrement": false
        },
        "fetched_at": {
          "name": "fetched_at",
          "type": "integer",
          "primaryKey": false,
          "notNull": true,
          "autoincrement": false
        },
        "created_at": {
          "name": "created_at",
          "type": "integer",
          "primaryKey": false,
          "notNull": true,
          "autoincrement": false,
          "default": "(unixepoch())"
        }
      },
      "indexes": {
        "currency_rates_base_idx": {
          "name": "currency_rates_base_idx",
          "columns": [
            "base_currency"
          ],
          "isUnique": false
        },
        "currency_rates_fetched_idx": {
          "name": "currency_rates_fetched_idx",
          "columns": [
            "fetched_at"
          ],
          "isUnique": false
        }
      },
      "foreignKeys": {},
      "compositePrimaryKeys": {},
      "uniqueConstraints": {},
      "checkConstraints": {}
    },
    "expense_participants": {
      "name": "expense_participants",
      "columns": {
        "id": {
          "name": "id",
          "type": "integer",
          "primaryKey": true,
          "notNull": true,
          "autoincrement": true
        },
        "expense_id": {
          "name": "expense_id",
          "type": "integer",
          "primaryKey": false,
          "notNull": true,
          "autoincrement": false
        },
        "member_id": {
          "name": "member_id",
          "type": "integer",
          "primaryKey": false,
          "notNull": true,
          "autoincrement": false
        },
        "share_amount": {
          "name": "share_amount",
          "type": "real",
          "primaryKey": false,
          "notNull": true,
          "autoincrement": false
        },
        "is_paid": {
          "name": "is_paid",
          "type": "integer",
          "primaryKey": false,
          "notNull": true,
          "autoincrement": false,
          "default": false
        },
        "created_at": {
          "name": "created_at",
          "type": "integer",
          "primaryKey": false,
          "notNull": true,
          "autoincrement": false,
          "default": "(unixepoch())"
        }
      },
      "indexes": {
        "exp_participants_expense_idx": {
          "name": "exp_participants_expense_idx",
          "columns": [
            "expense_id"
          ],
          "isUnique": false
        },
        "exp_participants_member_idx": {
          "name": "exp_participants_member_idx",
          "columns": [
            "member_id"
          ],
          "isUnique": false
        },
        "exp_participants_pair_idx": {
          "name": "exp_participants_pair_idx",
          "columns": [
            "expense_id",
            "member_id"
          ],
          "isUnique": false
        }
      },
      "foreignKeys": {},
      "compositePrimaryKeys": {},
      "uniqueConstraints": {},
      "checkConstraints": {}
    },
    "settlements": {
      "name": "settlements",
      "columns": {
        "id": {
          "name": "id",
          "type": "integer",
          "primaryKey": true,
          "notNull": true,
          "autoincrement": true
        },
        "itinerary_id": {
          "name": "itinerary_id",
          "type": "integer",
          "primaryKey": false,
          "notNull": true,
          "autoincrement": false
        },
        "from_member_id": {
          "name": "from_member_id",
          "type": "integer",
          "primaryKey": false,
          "notNull": true,
          "autoincrement": false
        },
        "to_member_id": {
          "name": "to_member_id",
          "type": "integer",
          "primaryKey": false,
          "notNull": true,
          "autoincrement": false
        },
        "amount": {
          "name": "amount",
          "type": "real",
          "primaryKey": false,
          "notNull": true,
          "autoincrement": false
        },
        "currency": {
          "name": "currency",
          "type": "text",
          "primaryKey": false,
          "notNull": true,
          "autoincrement": false,
          "default": "'CNY'"
        },
        "is_settled": {
          "name": "is_settled",
          "type": "integer",
          "primaryKey": false,
          "notNull": true,
          "autoincrement": false,
          "default": false
        },
        "settled_at": {
          "name": "settled_at",
          "type": "integer",
          "primaryKey": false,
          "notNull": false,
          "autoincrement": false
        },
        "created_at": {
          "name": "created_at",
          "type": "integer",
          "primaryKey": false,
          "notNull": true,
          "autoincrement": false,
          "default": "(unixepoch())"
        }
      },
      "indexes": {
        "settlements_itin_idx": {
          "name": "settlements_itin_idx",
          "columns": [
            "itinerary_id"
          ],
          "isUnique": false
        },
        "settlements_from_idx": {
          "name": "settlements_from_idx",
          "columns": [
            "from_member_id"
          ],
          "isUnique": false
        },
        "settlements_to_idx": {
          "name": "settlements_to_idx",
          "columns": [
            "to_member_id"
          ],
          "isUnique": false
        },
        "settlements_settled_idx": {
          "name": "settlements_settled_idx",
          "columns": [
            "is_settled"
          ],
          "isUnique": false
        }
      },
      "foreignKeys": {},
      "compositePrimaryKeys": {},
      "uniqueConstraints": {},
      "checkConstraints": {}
    },
    "shared_expenses": {
      "name": "shared_expenses",
      "columns": {
        "id": {
          "name": "id",
          "type": "integer",
          "primaryKey": true,
          "notNull": true,
          "autoincrement": true
        },
        "itinerary_id": {
          "name": "itinerary_id",
          "type": "integer",
          "primaryKey": false,
          "notNull": true,
          "autoincrement": false
        },
        "paid_by_member_id": {
          "name": "paid_by_member_id",
          "type": "integer",
          "primaryKey": false,
          "notNull": true,
          "autoincrement": false
        },
        "amount": {
          "name": "amount",
          "type": "real",
          "primaryKey": false,
          "notNull": true,
          "autoincrement": false
        },
        "currency": {
          "name": "currency",
          "type": "text",
          "primaryKey": false,
          "notNull": true,
          "autoincrement": false,
          "default": "'CNY'"
        },
        "category": {
          "name": "category",
          "type": "text",
          "primaryKey": false,
          "notNull": false,
          "autoincrement": false
        },
        "description": {
          "name": "description",
          "type": "text",
          "primaryKey": false,
          "notNull": false,
          "autoincrement": false
        },
        "date": {
          "name": "date",
          "type": "text",
          "primaryKey": false,
          "notNull": false,
          "autoincrement": false
        },
        "split_type": {
          "name": "split_type",
          "type": "text",
          "primaryKey": false,
          "notNull": true,
          "autoincrement": false,
          "default": "'equal'"
        },
        "created_at": {
          "name": "created_at",
          "type": "integer",
          "primaryKey": false,
          "notNull": true,
          "autoincrement": false,
          "default": "(unixepoch())"
        },
        "updated_at": {
          "name": "updated_at",
          "type": "integer",
          "primaryKey": false,
          "notNull": true,
          "autoincrement": false,
          "default": "(unixepoch())"
        }
      },
      "indexes": {
        "shared_exp_itin_idx": {
          "name": "shared_exp_itin_idx",
          "columns": [
            "itinerary_id"
          ],
          "isUnique": false
        },
        "shared_exp_itin_date_idx": {
          "name": "shared_exp_itin_date_idx",
          "columns": [
            "itinerary_id",
            "date"
          ],
          "isUnique": false
        },
        "shared_exp_paid_by_idx": {
          "name": "shared_exp_paid_by_idx",
          "columns": [
            "paid_by_member_id"
          ],
          "isUnique": false
        },
        "shared_exp_category_idx": {
          "name": "shared_exp_category_idx",
          "columns": [
            "category"
          ],
          "isUnique": false
        }
      },
      "foreignKeys": {},
      "compositePrimaryKeys": {},
      "uniqueConstraints": {},
      "checkConstraints": {}
    },
    "trip_members": {
      "name": "trip_members",
      "columns": {
        "id": {
          "name": "id",
          "type": "integer",
          "primaryKey": true,
          "notNull": true,
          "autoincrement": true
        },
        "itinerary_id": {
          "name": "itinerary_id",
          "type": "integer",
          "primaryKey": false,
          "notNull": true,
          "autoincrement": false
        },
        "user_id": {
          "name": "user_id",
          "type": "integer",
          "primaryKey": false,
          "notNull": false,
          "autoincrement": false
        },
        "name": {
          "name": "name",
          "type": "text",
          "primaryKey": false,
          "notNull": true,
          "autoincrement": false
        },
        "avatar_url": {
          "name": "avatar_url",
          "type": "text",
          "primaryKey": false,
          "notNull": false,
          "autoincrement": false
        },
        "is_registered": {
          "name": "is_registered",
          "type": "integer",
          "primaryKey": false,
          "notNull": true,
          "autoincrement": false,
          "default": false
        },
        "created_at": {
          "name": "created_at",
          "type": "integer",
          "primaryKey": false,
          "notNull": true,
          "autoincrement": false,
          "default": "(unixepoch())"
        }
      },
      "indexes": {
        "trip_members_itin_idx": {
          "name": "trip_members_itin_idx",
          "columns": [
            "itinerary_id"
          ],
          "isUnique": false
        },
        "trip_members_itin_user_idx": {
          "name": "trip_members_itin_user_idx",
          "columns": [
            "itinerary_id",
            "user_id"
          ],
          "isUnique": false
        },
        "trip_members_user_idx": {
          "name": "trip_members_user_idx",
          "columns": [
            "user_id"
          ],
          "isUnique": false
        }
      },
      "foreignKeys": {},
      "compositePrimaryKeys": {},
      "uniqueConstraints": {},
      "checkConstraints": {}
    },
    "expenses": {
      "name": "expenses",
      "columns": {
        "id": {
          "name": "id",
          "type": "integer",
          "primaryKey": true,
          "notNull": true,
          "autoincrement": true
        },
        "itinerary_id": {
          "name": "itinerary_id",
          "type": "integer",
          "primaryKey": false,
          "notNull": true,
          "autoincrement": false
        },
        "user_id": {
          "name": "user_id",
          "type": "integer",
          "primaryKey": false,
          "notNull": true,
          "autoincrement": false
        },
        "category_id": {
          "name": "category_id",
          "type": "integer",
          "primaryKey": false,
          "notNull": false,
          "autoincrement": false
        },
        "amount": {
          "name": "amount",
          "type": "real",
          "primaryKey": false,
          "notNull": true,
          "autoincrement": false
        },
        "currency": {
          "name": "currency",
          "type": "text",
          "primaryKey": false,
          "notNull": true,
          "autoincrement": false,
          "default": "'CNY'"
        },
        "description": {
          "name": "description",
          "type": "text",
          "primaryKey": false,
          "notNull": false,
          "autoincrement": false
        },
        "date": {
          "name": "date",
          "type": "text",
          "primaryKey": false,
          "notNull": true,
          "autoincrement": false
        },
        "created_at": {
          "name": "created_at",
          "type": "integer",
          "primaryKey": false,
          "notNull": true,
          "autoincrement": false,
          "default": "(unixepoch())"
        },
        "updated_at": {
          "name": "updated_at",
          "type": "integer",
          "primaryKey": false,
          "notNull": true,
          "autoincrement": false,
          "default": "(unixepoch())"
        }
      },
      "indexes": {
        "expenses_itinerary_idx": {
          "name": "expenses_itinerary_idx",
          "columns": [
            "itinerary_id"
          ],
          "isUnique": false
        },
        "expenses_user_idx": {
          "name": "expenses_user_idx",
          "columns": [
            "user_id"
          ],
          "isUnique": false
        },
        "expenses_category_idx": {
          "name": "expenses_category_idx",
          "columns": [
            "category_id"
          ],
          "isUnique": false
        },
        "expenses_itin_category_idx": {
          "name": "expenses_itin_category_idx",
          "columns": [
            "itinerary_id",
            "category_id"
          ],
          "isUnique": false
        },
        "expenses_date_idx": {
          "name": "expenses_date_idx",
          "columns": [
            "date"
          ],
          "isUnique": false
        }
      },
      "foreignKeys": {},
      "compositePrimaryKeys": {},
      "uniqueConstraints": {},
      "checkConstraints": {}
    },
    "itineraries": {
      "name": "itineraries",
      "columns": {
        "id": {
          "name": "id",
          "type": "integer",
          "primaryKey": true,
          "notNull": true,
          "autoincrement": true
        },
        "user_id": {
          "name": "user_id",
          "type": "integer",
          "primaryKey": false,
          "notNull": true,
          "autoincrement": false
        },
        "title": {
          "name": "title",
          "type": "text",
          "primaryKey": false,
          "notNull": true,
          "autoincrement": false
        },
        "city_id": {
          "name": "city_id",
          "type": "integer",
          "primaryKey": false,
          "notNull": true,
          "autoincrement": false
        },
        "start_date": {
          "name": "start_date",
          "type": "text",
          "primaryKey": false,
          "notNull": true,
          "autoincrement": false
        },
        "end_date": {
          "name": "end_date",
          "type": "text",
          "primaryKey": false,
          "notNull": true,
          "autoincrement": false
        },
        "visibility": {
          "name": "visibility",
          "type": "text",
          "primaryKey": false,
          "notNull": true,
          "autoincrement": false,
          "default": "'private'"
        },
        "cover_image_url": {
          "name": "cover_image_url",
          "type": "text",
          "primaryKey": false,
          "notNull": false,
          "autoincrement": false
        },
        "copied_from_id": {
          "name": "copied_from_id",
          "type": "integer",
          "primaryKey": false,
          "notNull": false,
          "autoincrement": false
        },
        "created_at": {
          "name": "created_at",
          "type": "integer",
          "primaryKey": false,
          "notNull": true,
          "autoincrement": false,
          "default": "(unixepoch())"
        },
        "updated_at": {
          "name": "updated_at",
          "type": "integer",
          "primaryKey": false,
          "notNull": true,
          "autoincrement": false,
          "default": "(unixepoch())"
        }
      },
      "indexes": {
        "itineraries_user_idx": {
          "name": "itineraries_user_idx",
          "columns": [
            "user_id"
          ],
          "isUnique": false
        },
        "itineraries_visibility_idx": {
          "name": "itineraries_visibility_idx",
          "columns": [
            "visibility"
          ],
          "isUnique": false
        },
        "itineraries_city_idx": {
          "name": "itineraries_city_idx",
          "columns": [
            "city_id"
          ],
          "isUnique": false
        },
        "itineraries_visibility_city_idx": {
          "name": "itineraries_visibility_city_idx",
          "columns": [
            "visibility",
            "city_id"
          ],
          "isUnique": false
        },
        "itineraries_user_visibility_idx": {
          "name": "itineraries_user_visibility_idx",
          "columns": [
            "user_id",
            "visibility"
          ],
          "isUnique": false
        }
      },
      "foreignKeys": {},
      "compositePrimaryKeys": {},
      "uniqueConstraints": {},
      "checkConstraints": {}
    },
    "itinerary_budgets": {
      "name": "itinerary_budgets",
      "columns": {
        "id": {
          "name": "id",
          "type": "integer",
          "primaryKey": true,
          "notNull": true,
          "autoincrement": true
        },
        "itinerary_id": {
          "name": "itinerary_id",
          "type": "integer",
          "primaryKey": false,
          "notNull": true,
          "autoincrement": false
        },
        "user_id": {
          "name": "user_id",
          "type": "integer",
          "primaryKey": false,
          "notNull": true,
          "autoincrement": false
        },
        "total_budget": {
          "name": "total_budget",
          "type": "real",
          "primaryKey": false,
          "notNull": false,
          "autoincrement": false
        },
        "currency": {
          "name": "currency",
          "type": "text",
          "primaryKey": false,
          "notNull": true,
          "autoincrement": false,
          "default": "'CNY'"
        },
        "category_budgets": {
          "name": "category_budgets",
          "type": "text",
          "primaryKey": false,
          "notNull": false,
          "autoincrement": false
        },
        "created_at": {
          "name": "created_at",
          "type": "integer",
          "primaryKey": false,
          "notNull": true,
          "autoincrement": false,
          "default": "(unixepoch())"
        },
        "updated_at": {
          "name": "updated_at",
          "type": "integer",
          "primaryKey": false,
          "notNull": true,
          "autoincrement": false,
          "default": "(unixepoch())"
        }
      },
      "indexes": {
        "itin_budgets_itinerary_idx": {
          "name": "itin_budgets_itinerary_idx",
          "columns": [
            "itinerary_id"
          ],
          "isUnique": false
        },
        "itin_budgets_user_idx": {
          "name": "itin_budgets_user_idx",
          "columns": [
            "user_id"
          ],
          "isUnique": false
        }
      },
      "foreignKeys": {},
      "compositePrimaryKeys": {},
      "uniqueConstraints": {},
      "checkConstraints": {}
    },
    "itinerary_collaborators": {
      "name": "itinerary_collaborators",
      "columns": {
        "id": {
          "name": "id",
          "type": "integer",
          "primaryKey": true,
          "notNull": true,
          "autoincrement": true
        },
        "user_id": {
          "name": "user_id",
          "type": "integer",
          "primaryKey": false,
          "notNull": true,
          "autoincrement": false
        },
        "itinerary_id": {
          "name": "itinerary_id",
          "type": "integer",
          "primaryKey": false,
          "notNull": true,
          "autoincrement": false
        },
        "role": {
          "name": "role",
          "type": "text",
          "primaryKey": false,
          "notNull": true,
          "autoincrement": false
        },
        "created_at": {
          "name": "created_at",
          "type": "integer",
          "primaryKey": false,
          "notNull": true,
          "autoincrement": false,
          "default": "(unixepoch())"
        },
        "updated_at": {
          "name": "updated_at",
          "type": "integer",
          "primaryKey": false,
          "notNull": true,
          "autoincrement": false,
          "default": "(unixepoch())"
        }
      },
      "indexes": {
        "itinerary_collabs_itinerary_idx": {
          "name": "itinerary_collabs_itinerary_idx",
          "columns": [
            "itinerary_id"
          ],
          "isUnique": false
        },
        "itinerary_collabs_user_idx": {
          "name": "itinerary_collabs_user_idx",
          "columns": [
            "user_id"
          ],
          "isUnique": false
        },
        "itinerary_collabs_uniq": {
          "name": "itinerary_collabs_uniq",
          "columns": [
            "itinerary_id",
            "user_id"
          ],
          "isUnique": true
        }
      },
      "foreignKeys": {},
      "compositePrimaryKeys": {},
      "uniqueConstraints": {},
      "checkConstraints": {}
    },
    "itinerary_days": {
      "name": "itinerary_days",
      "columns": {
        "id": {
          "name": "id",
          "type": "integer",
          "primaryKey": true,
          "notNull": true,
          "autoincrement": true
        },
        "itinerary_id": {
          "name": "itinerary_id",
          "type": "integer",
          "primaryKey": false,
          "notNull": true,
          "autoincrement": false
        },
        "day_number": {
          "name": "day_number",
          "type": "integer",
          "primaryKey": false,
          "notNull": true,
          "autoincrement": false
        },
        "date": {
          "name": "date",
          "type": "text",
          "primaryKey": false,
          "notNull": true,
          "autoincrement": false
        },
        "created_at": {
          "name": "created_at",
          "type": "integer",
          "primaryKey": false,
          "notNull": true,
          "autoincrement": false,
          "default": "(unixepoch())"
        },
        "updated_at": {
          "name": "updated_at",
          "type": "integer",
          "primaryKey": false,
          "notNull": true,
          "autoincrement": false,
          "default": "(unixepoch())"
        }
      },
      "indexes": {
        "itinerary_days_itinerary_idx": {
          "name": "itinerary_days_itinerary_idx",
          "columns": [
            "itinerary_id"
          ],
          "isUnique": false
        }
      },
      "foreignKeys": {},
      "compositePrimaryKeys": {},
      "uniqueConstraints": {},
      "checkConstraints": {}
    },
    "itinerary_items": {
      "name": "itinerary_items",
      "columns": {
        "id": {
          "name": "id",
          "type": "integer",
          "primaryKey": true,
          "notNull": true,
          "autoincrement": true
        },
        "day_id": {
          "name": "day_id",
          "type": "integer",
          "primaryKey": false,
          "notNull": true,
          "autoincrement": false
        },
        "poi_id": {
          "name": "poi_id",
          "type": "integer",
          "primaryKey": false,
          "notNull": true,
          "autoincrement": false
        },
        "order_index": {
          "name": "order_index",
          "type": "integer",
          "primaryKey": false,
          "notNull": true,
          "autoincrement": false
        },
        "start_time": {
          "name": "start_time",
          "type": "text",
          "primaryKey": false,
          "notNull": false,
          "autoincrement": false
        },
        "end_time": {
          "name": "end_time",
          "type": "text",
          "primaryKey": false,
          "notNull": false,
          "autoincrement": false
        },
        "transport_mode": {
          "name": "transport_mode",
          "type": "text",
          "primaryKey": false,
          "notNull": true,
          "autoincrement": false
        },
        "notes": {
          "name": "notes",
          "type": "text",
          "primaryKey": false,
          "notNull": false,
          "autoincrement": false
        },
        "created_at": {
          "name": "created_at",
          "type": "integer",
          "primaryKey": false,
          "notNull": true,
          "autoincrement": false,
          "default": "(unixepoch())"
        },
        "updated_at": {
          "name": "updated_at",
          "type": "integer",
          "primaryKey": false,
          "notNull": true,
          "autoincrement": false,
          "default": "(unixepoch())"
        }
      },
      "indexes": {
        "itinerary_items_day_idx": {
          "name": "itinerary_items_day_idx",
          "columns": [
            "day_id"
          ],
          "isUnique": false
        }
      },
      "foreignKeys": {},
      "compositePrimaryKeys": {},
      "uniqueConstraints": {},
      "checkConstraints": {}
    },
    "pois": {
      "name": "pois",
      "columns": {
        "id": {
          "name": "id",
          "type": "integer",
          "primaryKey": true,
          "notNull": true,
          "autoincrement": true
        },
        "external_id": {
          "name": "external_id",
          "type": "text",
          "primaryKey": false,
          "notNull": false,
          "autoincrement": false
        },
        "name": {
          "name": "name",
          "type": "text",
          "primaryKey": false,
          "notNull": true,
          "autoincrement": false
        },
        "name_en": {
          "name": "name_en",
          "type": "text",
          "primaryKey": false,
          "notNull": false,
          "autoincrement": false
        },
        "category": {
          "name": "category",
          "type": "text",
          "primaryKey": false,
          "notNull": true,
          "autoincrement": false
        },
        "city_id": {
          "name": "city_id",
          "type": "integer",
          "primaryKey": false,
          "notNull": true,
          "autoincrement": false
        },
        "address": {
          "name": "address",
          "type": "text",
          "primaryKey": false,
          "notNull": false,
          "autoincrement": false
        },
        "latitude": {
          "name": "latitude",
          "type": "real",
          "primaryKey": false,
          "notNull": true,
          "autoincrement": false
        },
        "longitude": {
          "name": "longitude",
          "type": "real",
          "primaryKey": false,
          "notNull": true,
          "autoincrement": false
        },
        "rating": {
          "name": "rating",
          "type": "real",
          "primaryKey": false,
          "notNull": false,
          "autoincrement": false
        },
        "rating_count": {
          "name": "rating_count",
          "type": "integer",
          "primaryKey": false,
          "notNull": true,
          "autoincrement": false,
          "default": 0
        },
        "price_level": {
          "name": "price_level",
          "type": "integer",
          "primaryKey": false,
          "notNull": false,
          "autoincrement": false
        },
        "business_hours": {
          "name": "business_hours",
          "type": "text",
          "primaryKey": false,
          "notNull": false,
          "autoincrement": false
        },
        "best_visit_time": {
          "name": "best_visit_time",
          "type": "text",
          "primaryKey": false,
          "notNull": false,
          "autoincrement": false
        },
        "phone": {
          "name": "phone",
          "type": "text",
          "primaryKey": false,
          "notNull": false,
          "autoincrement": false
        },
        "image_urls": {
          "name": "image_urls",
          "type": "text",
          "primaryKey": false,
          "notNull": false,
          "autoincrement": false
        },
        "source": {
          "name": "source",
          "type": "text",
          "primaryKey": false,
          "notNull": true,
          "autoincrement": false
        },
        "is_hidden_gem": {
          "name": "is_hidden_gem",
          "type": "integer",
          "primaryKey": false,
          "notNull": false,
          "autoincrement": false
        },
        "hidden_gem_score": {
          "name": "hidden_gem_score",
          "type": "real",
          "primaryKey": false,
          "notNull": false,
          "autoincrement": false
        },
        "hidden_gem_rating": {
          "name": "hidden_gem_rating",
          "type": "real",
          "primaryKey": false,
          "notNull": false,
          "autoincrement": false
        },
        "hidden_gem_rating_count": {
          "name": "hidden_gem_rating_count",
          "type": "integer",
          "primaryKey": false,
          "notNull": false,
          "autoincrement": false
        },
        "local_recommendation": {
          "name": "local_recommendation",
          "type": "text",
          "primaryKey": false,
          "notNull": false,
          "autoincrement": false
        },
        "popularity_level": {
          "name": "popularity_level",
          "type": "text",
          "primaryKey": false,
          "notNull": false,
          "autoincrement": false
        },
        "cuisine_type": {
          "name": "cuisine_type",
          "type": "text",
          "primaryKey": false,
          "notNull": false,
          "autoincrement": false
        },
        "is_local_favorite": {
          "name": "is_local_favorite",
          "type": "integer",
          "primaryKey": false,
          "notNull": false,
          "autoincrement": false
        },
        "signature_dishes": {
          "name": "signature_dishes",
          "type": "text",
          "primaryKey": false,
          "notNull": false,
          "autoincrement": false
        },
        "dietary_options": {
          "name": "dietary_options",
          "type": "text",
          "primaryKey": false,
          "notNull": false,
          "autoincrement": false
        },
        "average_price": {
          "name": "average_price",
          "type": "real",
          "primaryKey": false,
          "notNull": false,
          "autoincrement": false
        },
        "created_at": {
          "name": "created_at",
          "type": "integer",
          "primaryKey": false,
          "notNull": true,
          "autoincrement": false,
          "default": "(unixepoch())"
        },
        "updated_at": {
          "name": "updated_at",
          "type": "integer",
          "primaryKey": false,
          "notNull": true,
          "autoincrement": false,
          "default": "(unixepoch())"
        }
      },
      "indexes": {
        "pois_city_idx": {
          "name": "pois_city_idx",
          "columns": [
            "city_id"
          ],
          "isUnique": false
        },
        "pois_category_idx": {
          "name": "pois_category_idx",
          "columns": [
            "category"
          ],
          "isUnique": false
        },
        "pois_city_category_idx": {
          "name": "pois_city_category_idx",
          "columns": [
            "city_id",
            "category"
          ],
          "isUnique": false
        },
        "pois_external_source_idx": {
          "name": "pois_external_source_idx",
          "columns": [
            "external_id",
            "source"
          ],
          "isUnique": false
        },
        "pois_hidden_gem_idx": {
          "name": "pois_hidden_gem_idx",
          "columns": [
            "is_hidden_gem"
          ],
          "isUnique": false
        },
        "pois_city_hidden_gem_idx": {
          "name": "pois_city_hidden_gem_idx",
          "columns": [
            "city_id",
            "is_hidden_gem"
          ],
          "isUnique": false
        },
        "pois_popularity_idx": {
          "name": "pois_popularity_idx",
          "columns": [
            "popularity_level"
          ],
          "isUnique": false
        }
      },
      "foreignKeys": {},
      "compositePrimaryKeys": {},
      "uniqueConstraints": {},
      "checkConstraints": {}
    },
    "profiles": {
      "name": "profiles",
      "columns": {
        "id": {
          "name": "id",
          "type": "integer",
          "primaryKey": true,
          "notNull": true,
          "autoincrement": true
        },
        "user_id": {
          "name": "user_id",
          "type": "integer",
          "primaryKey": false,
          "notNull": true,
          "autoincrement": false
        },
        "email": {
          "name": "email",
          "type": "text",
          "primaryKey": false,
          "notNull": true,
          "autoincrement": false
        },
        "phone": {
          "name": "phone",
          "type": "text",
          "primaryKey": false,
          "notNull": false,
          "autoincrement": false
        },
        "display_name": {
          "name": "display_name",
          "type": "text",
          "primaryKey": false,
          "notNull": false,
          "autoincrement": false
        },
        "avatar_url": {
          "name": "avatar_url",
          "type": "text",
          "primaryKey": false,
          "notNull": false,
          "autoincrement": false
        },
        "bio": {
          "name": "bio",
          "type": "text",
          "primaryKey": false,
          "notNull": false,
          "autoincrement": false
        },
        "expo_push_token": {
          "name": "expo_push_token",
          "type": "text",
          "primaryKey": false,
          "notNull": false,
          "autoincrement": false
        },
        "created_at": {
          "name": "created_at",
          "type": "integer",
          "primaryKey": false,
          "notNull": true,
          "autoincrement": false,
          "default": "(unixepoch())"
        },
        "updated_at": {
          "name": "updated_at",
          "type": "integer",
          "primaryKey": false,
          "notNull": true,
          "autoincrement": false,
          "default": "(unixepoch())"
        }
      },
      "indexes": {
        "profiles_user_idx": {
          "name": "profiles_user_idx",
          "columns": [
            "user_id"
          ],
          "isUnique": false
        },
        "profiles_email_idx": {
          "name": "profiles_email_idx",
          "columns": [
            "email"
          ],
          "isUnique": false
        },
        "profiles_phone_idx": {
          "name": "profiles_phone_idx",
          "columns": [
            "phone"
          ],
          "isUnique": false
        }
      },
      "foreignKeys": {},
      "compositePrimaryKeys": {},
      "uniqueConstraints": {},
      "checkConstraints": {}
    },
    "share_event_logs": {
      "name": "share_event_logs",
      "columns": {
        "id": {
          "name": "id",
          "type": "integer",
          "primaryKey": true,
          "notNull": true,
          "autoincrement": true
        },
        "share_link_id": {
          "name": "share_link_id",
          "type": "integer",
          "primaryKey": false,
          "notNull": true,
          "autoincrement": false
        },
        "resource_type": {
          "name": "resource_type",
          "type": "text",
          "primaryKey": false,
          "notNull": true,
          "autoincrement": false
        },
        "resource_id": {
          "name": "resource_id",
          "type": "integer",
          "primaryKey": false,
          "notNull": true,
          "autoincrement": false
        },
        "event_type": {
          "name": "event_type",
          "type": "text",
          "primaryKey": false,
          "notNull": true,
          "autoincrement": false
        },
        "ip_address": {
          "name": "ip_address",
          "type": "text",
          "primaryKey": false,
          "notNull": false,
          "autoincrement": false
        },
        "user_agent": {
          "name": "user_agent",
          "type": "text",
          "primaryKey": false,
          "notNull": false,
          "autoincrement": false
        },
        "referrer": {
          "name": "referrer",
          "type": "text",
          "primaryKey": false,
          "notNull": false,
          "autoincrement": false
        },
        "created_at": {
          "name": "created_at",
          "type": "integer",
          "primaryKey": false,
          "notNull": true,
          "autoincrement": false,
          "default": "(unixepoch())"
        }
      },
      "indexes": {
        "share_logs_link_idx": {
          "name": "share_logs_link_idx",
          "columns": [
            "share_link_id"
          ],
          "isUnique": false
        },
        "share_logs_resource_idx": {
          "name": "share_logs_resource_idx",
          "columns": [
            "resource_type",
            "resource_id"
          ],
          "isUnique": false
        },
        "share_logs_created_idx": {
          "name": "share_logs_created_idx",
          "columns": [
            "created_at"
          ],
          "isUnique": false
        },
        "share_logs_type_idx": {
          "name": "share_logs_type_idx",
          "columns": [
            "event_type"
          ],
          "isUnique": false
        }
      },
      "foreignKeys": {},
      "compositePrimaryKeys": {},
      "uniqueConstraints": {},
      "checkConstraints": {}
    },
    "share_events": {
      "name": "share_events",
      "columns": {
        "id": {
          "name": "id",
          "type": "integer",
          "primaryKey": true,
          "notNull": true,
          "autoincrement": true
        },
        "resource_type": {
          "name": "resource_type",
          "type": "text",
          "primaryKey": false,
          "notNull": true,
          "autoincrement": false
        },
        "resource_id": {
          "name": "resource_id",
          "type": "integer",
          "primaryKey": false,
          "notNull": true,
          "autoincrement": false
        },
        "sharer_id": {
          "name": "sharer_id",
          "type": "integer",
          "primaryKey": false,
          "notNull": true,
          "autoincrement": false
        },
        "platform": {
          "name": "platform",
          "type": "text",
          "primaryKey": false,
          "notNull": false,
          "autoincrement": false
        },
        "event_type": {
          "name": "event_type",
          "type": "text",
          "primaryKey": false,
          "notNull": true,
          "autoincrement": false
        },
        "share_link_id": {
          "name": "share_link_id",
          "type": "integer",
          "primaryKey": false,
          "notNull": false,
          "autoincrement": false
        },
        "created_at": {
          "name": "created_at",
          "type": "integer",
          "primaryKey": false,
          "notNull": true,
          "autoincrement": false,
          "default": "(unixepoch())"
        }
      },
      "indexes": {
        "share_events_resource_idx": {
          "name": "share_events_resource_idx",
          "columns": [
            "resource_type",
            "resource_id"
          ],
          "isUnique": false
        },
        "share_events_sharer_idx": {
          "name": "share_events_sharer_idx",
          "columns": [
            "sharer_id"
          ],
          "isUnique": false
        },
        "share_events_platform_idx": {
          "name": "share_events_platform_idx",
          "columns": [
            "platform"
          ],
          "isUnique": false
        },
        "share_events_type_idx": {
          "name": "share_events_type_idx",
          "columns": [
            "event_type"
          ],
          "isUnique": false
        },
        "share_events_created_idx": {
          "name": "share_events_created_idx",
          "columns": [
            "created_at"
          ],
          "isUnique": false
        },
        "share_events_link_idx": {
          "name": "share_events_link_idx",
          "columns": [
            "share_link_id"
          ],
          "isUnique": false
        }
      },
      "foreignKeys": {},
      "compositePrimaryKeys": {},
      "uniqueConstraints": {},
      "checkConstraints": {}
    },
    "share_links": {
      "name": "share_links",
      "columns": {
        "id": {
          "name": "id",
          "type": "integer",
          "primaryKey": true,
          "notNull": true,
          "autoincrement": true
        },
        "share_code": {
          "name": "share_code",
          "type": "text",
          "primaryKey": false,
          "notNull": true,
          "autoincrement": false
        },
        "resource_type": {
          "name": "resource_type",
          "type": "text",
          "primaryKey": false,
          "notNull": true,
          "autoincrement": false
        },
        "resource_id": {
          "name": "resource_id",
          "type": "integer",
          "primaryKey": false,
          "notNull": true,
          "autoincrement": false
        },
        "owner_id": {
          "name": "owner_id",
          "type": "integer",
          "primaryKey": false,
          "notNull": true,
          "autoincrement": false
        },
        "is_active": {
          "name": "is_active",
          "type": "integer",
          "primaryKey": false,
          "notNull": true,
          "autoincrement": false,
          "default": true
        },
        "expires_at": {
          "name": "expires_at",
          "type": "integer",
          "primaryKey": false,
          "notNull": false,
          "autoincrement": false
        },
        "view_count": {
          "name": "view_count",
          "type": "integer",
          "primaryKey": false,
          "notNull": true,
          "autoincrement": false,
          "default": 0
        },
        "metadata": {
          "name": "metadata",
          "type": "text",
          "primaryKey": false,
          "notNull": false,
          "autoincrement": false
        },
        "created_at": {
          "name": "created_at",
          "type": "integer",
          "primaryKey": false,
          "notNull": true,
          "autoincrement": false,
          "default": "(unixepoch())"
        }
      },
      "indexes": {
        "share_links_code_idx": {
          "name": "share_links_code_idx",
          "columns": [
            "share_code"
          ],
          "isUnique": false
        },
        "share_links_resource_idx": {
          "name": "share_links_resource_idx",
          "columns": [
            "resource_type",
            "resource_id"
          ],
          "isUnique": false
        },
        "share_links_owner_idx": {
          "name": "share_links_owner_idx",
          "columns": [
            "owner_id"
          ],
          "isUnique": false
        },
        "share_links_owner_resource_idx": {
          "name": "share_links_owner_resource_idx",
          "columns": [
            "owner_id",
            "resource_type",
            "resource_id"
          ],
          "isUnique": false
        },
        "share_links_active_idx": {
          "name": "share_links_active_idx",
          "columns": [
            "is_active"
          ],
          "isUnique": false
        },
        "share_links_expires_idx": {
          "name": "share_links_expires_idx",
          "columns": [
            "expires_at"
          ],
          "isUnique": false
        }
      },
      "foreignKeys": {},
      "compositePrimaryKeys": {},
      "uniqueConstraints": {},
      "checkConstraints": {}
    }
  },
  "views": {},
  "enums": {},
  "_meta": {
    "schemas": {},
    "tables": {},
    "columns": {}
  },
  "internal": {
    "indexes": {}
  }
}
